xocto/__init__.py
xocto/exceptions.py
xocto/health.py
xocto/localtime.py
xocto/numbers.py
xocto/pact_testing.py
xocto/py.typed
xocto/ranges.py
xocto/settlement_periods.py
xocto/urls.py
xocto/events/__init__.py
xocto/events/core.py
xocto/events/utils.py
xocto/fields/__init__.py
xocto/fields/postgres/__init__.py
xocto/fields/postgres/ranges.py
xocto/storage/__init__.py
xocto/storage/files.py
xocto/storage/s3_select.py
xocto/storage/storage.py
xocto/types/__init__.py
xocto/types/django.py
xocto/types/generic.py
xocto-8.5.1.dist-info/licenses/LICENSE
xocto-8.5.1.dist-info/METADATA
xocto-8.5.1.dist-info/WHEEL
xocto-8.5.1.dist-info/top_level.txt
xocto-8.5.1.dist-info/RECORD
